ligo/skymap/__init__.py
ligo/skymap/conftest.py
ligo/skymap/core.abi3.so
ligo/skymap/distance.py
ligo/skymap/dpgmm.py
ligo/skymap/healpix_tree.py
ligo/skymap/kde.py
ligo/skymap/moc.py
ligo/skymap/version.py
ligo/skymap/bayestar/__init__.py
ligo/skymap/bayestar/ez_emcee.py
ligo/skymap/bayestar/filter.py
ligo/skymap/bayestar/interpolation.py
ligo/skymap/bayestar/tests/__init__.py
ligo/skymap/bayestar/tests/test_bayestar.py
ligo/skymap/bayestar/tests/test_interpolation.py
ligo/skymap/bayestar/tests/test_signal_amplitude_model.py
ligo/skymap/coordinates/__init__.py
ligo/skymap/coordinates/detector.py
ligo/skymap/coordinates/eigenframe.py
ligo/skymap/coordinates/tests/__init__.py
ligo/skymap/coordinates/tests/test_detector.py
ligo/skymap/extern/__init__.py
ligo/skymap/extern/numpy/__init__.py
ligo/skymap/extern/numpy/quantile.py
ligo/skymap/extern/ptemcee/__init__.py
ligo/skymap/extern/ptemcee/interruptible_pool.py
ligo/skymap/extern/ptemcee/mpi_pool.py
ligo/skymap/extern/ptemcee/sampler.py
ligo/skymap/extern/ptemcee/tests.py
ligo/skymap/extern/ptemcee/util.py
ligo/skymap/io/__init__.py
ligo/skymap/io/fits.py
ligo/skymap/io/hdf5.py
ligo/skymap/io/events/__init__.py
ligo/skymap/io/events/base.py
ligo/skymap/io/events/detector_disabled.py
ligo/skymap/io/events/gracedb.py
ligo/skymap/io/events/hdf.py
ligo/skymap/io/events/ligolw.py
ligo/skymap/io/events/magic.py
ligo/skymap/io/events/sqlite.py
ligo/skymap/io/tests/__init__.py
ligo/skymap/io/tests/test_io_events.py
ligo/skymap/io/tests/data/2016_subset.xml.gz
ligo/skymap/io/tests/data/G197392_coinc.xml.gz
ligo/skymap/io/tests/data/G197392_psd.xml.gz
ligo/skymap/io/tests/data/G211117_coinc.xml.gz
ligo/skymap/io/tests/data/G211117_psd.xml.gz
ligo/skymap/io/tests/data/__init__.py
ligo/skymap/io/tests/data/test.hdf5
ligo/skymap/io/tests/data/gstlal_reference_psd/H1L1V1-REFERENCE_PSD-967234210-29963.xml.gz
ligo/skymap/io/tests/data/gstlal_reference_psd/__init__.py
ligo_skymap-2.5.0.dist-info/METADATA
ligo_skymap-2.5.0.dist-info/WHEEL
ligo_skymap-2.5.0.dist-info/entry_points.txt
ligo_skymap-2.5.0.dist-info/top_level.txt
ligo_skymap-2.5.0.dist-info/RECORD
