Metadata-Version: 2.4
Name: ligo.skymap
Version: 2.5.0
Summary: Tools for reading, writing, manipulating, and making LIGO/Virgo/KAGRA sky maps
Author-email: Leo Singer <leo.singer@ligo.org>
License-Expression: GPL-3.0-or-later
Project-URL: homepage, https://lscsoft.docs.ligo.org/ligo.skymap/
Project-URL: Bug Tracker, https://git.ligo.org/lscsoft/ligo.skymap/issues
Project-URL: Change Log, https://lscsoft.docs.ligo.org/ligo.skymap/changes.html
Project-URL: Documentation, https://lscsoft.docs.ligo.org/ligo.skymap
Project-URL: GitHub, https://github.com/lpsinger/ligo.skymap
Project-URL: Source Code, https://git.ligo.org/lscsoft/ligo.skymap
Classifier: Development Status :: 5 - Production/Stable
Classifier: Intended Audience :: Science/Research
Classifier: Operating System :: MacOS
Classifier: Operating System :: POSIX
Classifier: Operating System :: POSIX :: Linux
Classifier: Operating System :: Unix
Classifier: Programming Language :: C
Classifier: Programming Language :: Python :: 3
Classifier: Programming Language :: Python :: 3.11
Classifier: Programming Language :: Python :: 3.12
Classifier: Programming Language :: Python :: 3.13
Classifier: Topic :: Scientific/Engineering :: Astronomy
Classifier: Topic :: Scientific/Engineering :: Physics
Requires-Python: >=3.11
Requires-Dist: astroplan>=0.7
Requires-Dist: astropy>=6.0
Requires-Dist: astropy-healpix>=0.3
Requires-Dist: healpy
Requires-Dist: h5py
Requires-Dist: igwn-ligolw
Requires-Dist: igwn-segments
Requires-Dist: lalsuite>=7.26
Requires-Dist: ligo-gracedb>=2.0.1
Requires-Dist: matplotlib>=3.9.1
Requires-Dist: networkx
Requires-Dist: numpy>=2.0.0
Requires-Dist: pillow>=2.5.0
Requires-Dist: pytz
Requires-Dist: reproject>=0.3.2
Requires-Dist: scipy>=1.10.1
Requires-Dist: shapely>=2.0.0
Requires-Dist: tqdm>=4.27.0
Provides-Extra: test
Requires-Dist: astroquery; extra == "test"
Requires-Dist: figaro>=1.7.8; extra == "test"
Requires-Dist: pytest-astropy; extra == "test"
Requires-Dist: pytest-benchmark; extra == "test"
Requires-Dist: pytest-mpl; extra == "test"
Requires-Dist: pytest-rerunfailures; extra == "test"
Provides-Extra: docs
Requires-Dist: sphinx>=4.0; extra == "docs"
Requires-Dist: sphinx-argparse>=0.3.0; extra == "docs"
Requires-Dist: sphinx-astropy; extra == "docs"
Requires-Dist: sphinxcontrib-mermaid>=0.7.1; extra == "docs"
Provides-Extra: dpgmm
Requires-Dist: figaro>=1.7.8; extra == "dpgmm"
